AUTHORS
LICENSE
MANIFEST.in
README.md
setup.py
django_tastypie_oauth.egg-info/PKG-INFO
django_tastypie_oauth.egg-info/SOURCES.txt
django_tastypie_oauth.egg-info/dependency_links.txt
django_tastypie_oauth.egg-info/not-zip-safe
django_tastypie_oauth.egg-info/requires.txt
django_tastypie_oauth.egg-info/top_level.txt
requirements/base.txt
requirements/base.txt~
requirements/dev.txt
requirements/test.txt
requirements/test.txt~
tastypie_oauth/__init__.py
tastypie_oauth/authentication.py