Metadata-Version: 1.1
Name: django-tastypie-oauth
Version: 0.0.3
Summary: Providing OAuth services for Tastypie APIs
Home-page: https://github.com/orcasgit/django-tastypie-oauth
Author: Oregon Center for Applied Science
Author-email: bpitcher@orcasinc.com
License: Apache 2.0
Platform: UNKNOWN
Classifier: Development Status :: 4 - Beta
Classifier: Environment :: Web Environment
Classifier: Framework :: Django
Classifier: Intended Audience :: Developers
Classifier: License :: OSI Approved :: Apache Software License
Classifier: Operating System :: OS Independent
Classifier: Programming Language :: Python
Classifier: Programming Language :: Python :: 2.6
Classifier: Programming Language :: Python :: 2.7
Classifier: Programming Language :: Python :: 3.3
Classifier: Programming Language :: Python :: 3.4
Classifier: Topic :: Software Development :: Libraries :: Python Modules
